{
  "routes": [
    {
      "method": "GET",
      "path": "/dammis",
      "handler": "dammi.find",
      "config": {
        "policies": []
      }
    },
    {
      "method": "GET",
      "path": "/dammis/count",
      "handler": "dammi.count",
      "config": {
        "policies": []
      }
    },
    {
      "method": "GET",
      "path": "/dammis/:id",
      "handler": "dammi.findOne",
      "config": {
        "policies": []
      }
    },
    {
      "method": "POST",
      "path": "/dammis",
      "handler": "dammi.create",
      "config": {
        "policies": []
      }
    },
    {
      "method": "PUT",
      "path": "/dammis/:id",
      "handler": "dammi.update",
      "config": {
        "policies": []
      }
    },
    {
      "method": "DELETE",
      "path": "/dammis/:id",
      "handler": "dammi.delete",
      "config": {
        "policies": []
      }
    }
  ]
}
